{
  "vscode-html-language-server": {
    "command": "cmd.exe",
    "args": ["/c", "%APPDATA%\\npm\\vscode-html-language-server.cmd", "--stdio"],
    "extensionToLanguage": {
      ".html": "html",
      ".htm": "html"
    }
  },
  "vscode-css-language-server": {
    "command": "cmd.exe",
    "args": ["/c", "%APPDATA%\\npm\\vscode-css-language-server.cmd", "--stdio"],
    "extensionToLanguage": {
      ".css": "css",
      ".scss": "scss",
      ".less": "less"
    }
  },
  "vscode-json-language-server": {
    "command": "cmd.exe",
    "args": ["/c", "%APPDATA%\\npm\\vscode-json-language-server.cmd", "--stdio"],
    "extensionToLanguage": {
      ".json": "json",
      ".jsonc": "jsonc"
    }
  },
  "vscode-eslint-language-server": {
    "command": "cmd.exe",
    "args": ["/c", "%APPDATA%\\npm\\vscode-eslint-language-server.cmd", "--stdio"],
    "extensionToLanguage": {
      ".js": "javascript",
      ".jsx": "javascriptreact",
      ".ts": "typescript",
      ".tsx": "typescriptreact"
    }
  }
}
